{
    "Name": "Player1",
    "CurrentHealth": 100.0,
    "MaxHealth": 100.0,
    "CurrentMana": 100.0,
    "MaxMana": 100.0,
    "JumpHeight": 23.0,
    "CurrentStamina": 1000.8935546875,
    "MaxStamina": 1000.0,
    "StaminaBonusSpeed": 40.0,
    "StaminaRechargeRate": 0.010999999940395356,
    "StaminaUseRate": 6.0,
    "CurrentSpeed": 2.5,
    "BaseMovementSpeed": 2.5,
    "Reach": 2.0,
    "TargetRange": 5.0,
    "CanFight": true,
    "IsPlayer": true,
    "IsFollower": true,
    "IsFollowing": false,
    "idle_animation": "Idle01",
    "walking_forward_animation": "Walking",
    "running_forward_animation": "Running",
    "walking_backward_animation": "m_walking_backwards",
    "running_backward_animation": "m_running_backwards",
    "landing_animation": "Landing",
    "midair_animation": "MidAir",
    "jump_animation": "Jump",
    "x_pos": 12.93433666229248,
    "y_pos": -0.01500028371810913,
    "z_pos": 30.298471450805665,
    "id": "c72ca895-d671-4c93-9c2f-c457e8f6ac19",
    "squadLeaderId": ""
}